foxhole/__init__.py
foxhole/cli.py
foxhole/config.py
foxhole/install.py
foxhole/prune.py
foxhole-0.1.4.dist-info/licenses/LICENSE
foxhole-0.1.4.dist-info/METADATA
foxhole-0.1.4.dist-info/WHEEL
foxhole-0.1.4.dist-info/entry_points.txt
foxhole-0.1.4.dist-info/top_level.txt
foxhole-0.1.4.dist-info/RECORD
