Metadata-Version: 2.4
Name: foxhole
Version: 0.1.4
Summary: Text search for Firefox history
Author-email: Gustaf Gren <6107181+skogsgren@users.noreply.github.com>
License-File: LICENSE
Provides-Extra: dev
Requires-Dist: pytest; extra == "dev"
Dynamic: license-file
